agentjoy_bridge/__init__.py
agentjoy_bridge/__main__.py
agentjoy_bridge/cli.py
agentjoy_bridge-0.3.36.dist-info/METADATA
agentjoy_bridge-0.3.36.dist-info/WHEEL
agentjoy_bridge-0.3.36.dist-info/entry_points.txt
agentjoy_bridge-0.3.36.dist-info/top_level.txt
agentjoy_bridge-0.3.36.dist-info/RECORD
