Metadata-Version: 2.4
Name: agentjoy-bridge
Version: 0.3.36
Summary: AgentJoy Bridge CLI (Codex / Claude Code / Agent tool activity -> AgentJoy Runs)
Author: VNL Works
License: MIT
Project-URL: Homepage, https://vnlworks.com/store
Project-URL: Documentation, https://vnlworks.com/store
Project-URL: Support, https://vnlworks.com/store
Keywords: ai,agent,observability,ux,codex,claude,mcp
Classifier: License :: OSI Approved :: MIT License
Classifier: Programming Language :: Python :: 3
Classifier: Programming Language :: Python :: 3 :: Only
Classifier: Environment :: Console
Classifier: Topic :: Software Development :: Libraries
Requires-Python: >=3.9
